lelu_admin_test/__init__.py
lelu_admin_test/apps.py
lelu_admin_test/models.py
lelu_admin_test/settings.py
lelu_admin_test/urls.py
lelu_admin_test/management/__init__.py
lelu_admin_test/management/commands/__init__.py
lelu_admin_test/management/commands/generate_plugins.py
lelu_admin_test/migrations/0001_initial.py
lelu_admin_test/migrations/__init__.py
lelu_admin_test/views/__init__.py
lelu_admin_test/views/test_plugin.py
lelu_admin_test-1.0.4.dist-info/LICENSE
lelu_admin_test-1.0.4.dist-info/METADATA
lelu_admin_test-1.0.4.dist-info/WHEEL
lelu_admin_test-1.0.4.dist-info/top_level.txt
lelu_admin_test-1.0.4.dist-info/RECORD
