Metadata-Version: 2.2
Name: lelu_admin_test
Version: 1.0.4
Summary: 插件测试
Home-page: https://gitee.com/FireworksWD/lelu-admin-plugin
Author: DVAdmin
Author-email: 
Classifier: Programming Language :: Python :: 3
Classifier: License :: OSI Approved :: MIT License
Classifier: Operating System :: OS Independent
Requires-Python: >=3.9, <4
License-File: LICENSE
Dynamic: author
Dynamic: classifier
Dynamic: description
Dynamic: description-content-type
Dynamic: home-page
Dynamic: requires-python
Dynamic: summary
